clip_gaze/__init__.py
clip_gaze/artists_by_name.py
clip_gaze/artists_by_prevalence.py
clip_gaze/blip.py
clip_gaze/gaze.py
clip_gaze/media.py
clip_gaze/movements.py
clip_gaze/qualities.py
clip_gaze/sites.py
clip_gaze/BLIP/eval_nocaps.py
clip_gaze/BLIP/eval_retrieval_video.py
clip_gaze/BLIP/predict.py
clip_gaze/BLIP/pretrain.py
clip_gaze/BLIP/train_caption.py
clip_gaze/BLIP/train_nlvr.py
clip_gaze/BLIP/train_retrieval.py
clip_gaze/BLIP/train_vqa.py
clip_gaze/BLIP/utils.py
clip_gaze/BLIP/data/__init__.py
clip_gaze/BLIP/data/coco_karpathy_dataset.py
clip_gaze/BLIP/data/flickr30k_dataset.py
clip_gaze/BLIP/data/nlvr_dataset.py
clip_gaze/BLIP/data/nocaps_dataset.py
clip_gaze/BLIP/data/pretrain_dataset.py
clip_gaze/BLIP/data/utils.py
clip_gaze/BLIP/data/video_dataset.py
clip_gaze/BLIP/data/vqa_dataset.py
clip_gaze/BLIP/models/__init__.py
clip_gaze/BLIP/models/blip.py
clip_gaze/BLIP/models/blip_itm.py
clip_gaze/BLIP/models/blip_nlvr.py
clip_gaze/BLIP/models/blip_pretrain.py
clip_gaze/BLIP/models/blip_retrieval.py
clip_gaze/BLIP/models/blip_vqa.py
clip_gaze/BLIP/models/med.py
clip_gaze/BLIP/models/nlvr_encoder.py
clip_gaze/BLIP/models/vit.py
clip_gaze/BLIP/transform/randaugment.py
clip_gaze-0.3.0.dist-info/LICENSE
clip_gaze-0.3.0.dist-info/METADATA
clip_gaze-0.3.0.dist-info/WHEEL
clip_gaze-0.3.0.dist-info/top_level.txt
clip_gaze-0.3.0.dist-info/RECORD
