Metadata-Version: 2.1
Name: clip-gaze
Version: 0.3.0
Summary: Compare image prompts using CLIP
License: MIT
Project-URL: Homepage, https://github.com/hmillerbakewell/clip-gaze
Project-URL: Bug Tracker, https://github.com/hmillerbakewell/clip-gaze/issues
Keywords: clip,art,art analysis
Classifier: License :: OSI Approved :: MIT License
Classifier: Programming Language :: Python :: 3
Classifier: Programming Language :: Python :: 3.8
License-File: LICENSE
Requires-Dist: transformers
Requires-Dist: torch
